MANIFEST.in
README.md
README.rst
requirements.txt
setup.cfg
setup.py
Flask_Task_Monitor.egg-info/PKG-INFO
Flask_Task_Monitor.egg-info/SOURCES.txt
Flask_Task_Monitor.egg-info/dependency_links.txt
Flask_Task_Monitor.egg-info/requires.txt
Flask_Task_Monitor.egg-info/top_level.txt
flask_monitor/__init__.py
flask_monitor/base.py
flask_monitor/db_monitor.py
tests/__init__.py
tests/test.db
venv/lib/python3.6/collections/__pycache__/__init__.cpython-36.pyc
venv/lib/python3.6/collections/__pycache__/abc.cpython-36.pyc
venv/lib/python3.6/encodings/__pycache__/__init__.cpython-36.pyc
venv/lib/python3.6/encodings/__pycache__/aliases.cpython-36.pyc
venv/lib/python3.6/encodings/__pycache__/ascii.cpython-36.pyc
venv/lib/python3.6/encodings/__pycache__/charmap.cpython-36.pyc
venv/lib/python3.6/encodings/__pycache__/cp1252.cpython-36.pyc
venv/lib/python3.6/encodings/__pycache__/cp437.cpython-36.pyc
venv/lib/python3.6/encodings/__pycache__/euc_jp.cpython-36.pyc
venv/lib/python3.6/encodings/__pycache__/idna.cpython-36.pyc
venv/lib/python3.6/encodings/__pycache__/koi8_r.cpython-36.pyc
venv/lib/python3.6/encodings/__pycache__/latin_1.cpython-36.pyc
venv/lib/python3.6/encodings/__pycache__/raw_unicode_escape.cpython-36.pyc
venv/lib/python3.6/encodings/__pycache__/unicode_escape.cpython-36.pyc
venv/lib/python3.6/encodings/__pycache__/utf_16_be.cpython-36.pyc
venv/lib/python3.6/encodings/__pycache__/utf_16_le.cpython-36.pyc
venv/lib/python3.6/encodings/__pycache__/utf_32_be.cpython-36.pyc
venv/lib/python3.6/encodings/__pycache__/utf_32_le.cpython-36.pyc
venv/lib/python3.6/encodings/__pycache__/utf_8.cpython-36.pyc
venv/lib/python3.6/importlib/__pycache__/__init__.cpython-36.pyc
venv/lib/python3.6/importlib/__pycache__/_bootstrap.cpython-36.pyc
venv/lib/python3.6/importlib/__pycache__/_bootstrap_external.cpython-36.pyc
venv/lib/python3.6/importlib/__pycache__/abc.cpython-36.pyc
venv/lib/python3.6/importlib/__pycache__/machinery.cpython-36.pyc
venv/lib/python3.6/importlib/__pycache__/util.cpython-36.pyc