Metadata-Version: 1.1
Name: Flask-Task-Monitor
Version: 2.0
Summary: Flask Task Monitor module
Home-page: http://github.com/nonetheless/Flask-Task-Monitor
Author: nonetheless
Author-email: UNKNOWN
License: MIT
Keywords: utility,versioning
Platform: UNKNOWN
Classifier: Development Status :: 4 - Beta
Classifier: Environment :: Console
Classifier: Intended Audience :: Developers
Classifier: Operating System :: OS Independent
Classifier: Programming Language :: Python
Classifier: Programming Language :: Python :: 3.5
Classifier: Programming Language :: Python :: 3.6
Classifier: Programming Language :: Python :: 3.7
Classifier: Topic :: Software Development :: Libraries :: Python Modules
